LICENSE
MANIFEST.in
README.rst
setup.cfg
setup.py
solstice/__init__.py
solstice/bootstrap/__init__.py
solstice/bootstrap/__version__.py
solstice/bootstrap/houdini/OPMenu.xml
solstice/bootstrap/houdini/__init__.py
solstice/bootstrap/houdini/userSetup.py
solstice/bootstrap/maya/__init__.py
solstice/bootstrap/maya/userSetup.py
solstice_bootstrap.egg-info/PKG-INFO
solstice_bootstrap.egg-info/SOURCES.txt
solstice_bootstrap.egg-info/dependency_links.txt
solstice_bootstrap.egg-info/not-zip-safe
solstice_bootstrap.egg-info/requires.txt
solstice_bootstrap.egg-info/top_level.txt
tests/__init__.py
tests/test_bootstrap.py