Metadata-Version: 2.1
Name: solstice-bootstrap
Version: 0.0.2
Summary: Repository that contains source code for Solstice Bootstrap
Home-page: UNKNOWN
Author: Tomas Poveda
Author-email: tpovedatd@gmail.com
License: MIT
Platform: UNKNOWN
Provides-Extra: dev
Provides-Extra: test
